roboid/__init__.py
roboid/albert_ai.py
roboid/albert_ai_roboid.py
roboid/connector.py
roboid/hamster.py
roboid/hamster_roboid.py
roboid/hamster_s.py
roboid/hamster_s_roboid.py
roboid/keyboard.py
roboid/model.py
roboid/runner.py
roboid/scanner.py
roboid/serial_connector.py
roboid/serial_queue.py
roboid/turtle.py
roboid/turtle_roboid.py
roboid/util.py
pyroboid-1.5.4.dist-info/LICENSE
pyroboid-1.5.4.dist-info/METADATA
pyroboid-1.5.4.dist-info/WHEEL
pyroboid-1.5.4.dist-info/top_level.txt
pyroboid-1.5.4.dist-info/RECORD
