Metadata-Version: 2.1
Name: pyroboid
Version: 1.5.4
Summary: Python Package for Hamster, Hamster-S, Turtle, and Albert Ai
Home-page: https://github.com/hamsterschool/pyroboid
Author: Kwang-Hyun Park
Author-email: akaii@kw.ac.kr
License: UNKNOWN
Platform: UNKNOWN
Classifier: License :: OSI Approved :: GNU Lesser General Public License v2 or later (LGPLv2+)
Requires-Python: >=3
Requires-Dist: pyserial
